ERVsearch/Bed.py
ERVsearch/ERVsearch
ERVsearch/ERVsearch.py
ERVsearch/Errors.py
ERVsearch/Exonerate.py
ERVsearch/Fasta.py
ERVsearch/HelperFunctions.py
ERVsearch/ORFs.py
ERVsearch/Regions.py
ERVsearch/Summary.py
ERVsearch/Trees.py
ERVsearch/__init__.py
ERVsearch/_version.py
ERVsearch/ERV_db/all_ERVs_aa.fasta
ERVsearch/ERV_db/all_ERVs_nt.fasta
ERVsearch/ERV_db/convert.tsv
ERVsearch/ERV_db/env.fasta
ERVsearch/ERV_db/gag.fasta
ERVsearch/ERV_db/pol.fasta
ERVsearch/ERV_db/.ipynb_checkpoints/Untitled-checkpoint.ipynb
ERVsearch/phylogenies/outgroups.tsv
ERVsearch/phylogenies/group_phylogenies/ALV-like_alpha_gag.fasta
ERVsearch/phylogenies/group_phylogenies/ALV-like_alpha_pol.fasta
ERVsearch/phylogenies/group_phylogenies/Avian_alpha_gag.fasta
ERVsearch/phylogenies/group_phylogenies/Avian_alpha_pol.fasta
ERVsearch/phylogenies/group_phylogenies/Avian_beta_pol.fasta
ERVsearch/phylogenies/group_phylogenies/Avian_gamma_pol.fasta
ERVsearch/phylogenies/group_phylogenies/ERVL-like_spuma_pol.fasta
ERVsearch/phylogenies/group_phylogenies/FIV1_lenti_env.fasta
ERVsearch/phylogenies/group_phylogenies/FIV1_lenti_pol.fasta
ERVsearch/phylogenies/group_phylogenies/FIV2_lenti_pol.fasta
ERVsearch/phylogenies/group_phylogenies/FIV_lenti_gag.fasta
ERVsearch/phylogenies/group_phylogenies/Fish-Amphibian1_epsilon_pol.fasta
ERVsearch/phylogenies/group_phylogenies/FishAmphibian1_epsilon_pol.fasta
ERVsearch/phylogenies/group_phylogenies/FishReptile1_epsilon_pol.fasta
ERVsearch/phylogenies/group_phylogenies/GALV-like_gamma_env.fasta
ERVsearch/phylogenies/group_phylogenies/GALV-like_gamma_gag.fasta
ERVsearch/phylogenies/group_phylogenies/GALV-like_gamma_pol.fasta
ERVsearch/phylogenies/group_phylogenies/HERVF-like_gamma_gag.fasta
ERVsearch/phylogenies/group_phylogenies/HERVI-like_gamma_pol.fasta
ERVsearch/phylogenies/group_phylogenies/HERVK-like_beta_env.fasta
ERVsearch/phylogenies/group_phylogenies/HERVK-like_beta_gag.fasta
ERVsearch/phylogenies/group_phylogenies/HERVK-like_beta_pol.fasta
ervsearch-1.0.12.dist-info/LICENSE
ervsearch-1.0.12.dist-info/METADATA
ervsearch-1.0.12.dist-info/WHEEL
ervsearch-1.0.12.dist-info/top_level.txt
ervsearch-1.0.12.dist-info/RECORD
