Metadata-Version: 2.1
Name: ervsearch
Version: 1.0.12
Summary: Tool for identifying endogenous retrovirus like regions in a set of sequences
Home-page: https://github.com/KatyBrown/ERVsearch
Author: Katy Brown
Author-email: kab84@cam.ac.uk
License: UNKNOWN
Platform: UNKNOWN
Classifier: Programming Language :: Python :: 3
Classifier: License :: OSI Approved :: MIT License
Classifier: Operating System :: OS Independent
Requires-Dist: numpy
Requires-Dist: matplotlib
Requires-Dist: ruffus
Requires-Dist: pandas
Requires-Dist: ete3
